emacs_porthole/__init__.py
emacs_porthole/core.py
emacs_porthole/exceptions.py
emacs_porthole/json_rpc.py
emacs_porthole/utils.py
emacs_porthole-0.3.1.dist-info/AUTHORS
emacs_porthole-0.3.1.dist-info/LICENSE.txt
emacs_porthole-0.3.1.dist-info/METADATA
emacs_porthole-0.3.1.dist-info/WHEEL
emacs_porthole-0.3.1.dist-info/top_level.txt
emacs_porthole-0.3.1.dist-info/RECORD
